omero_arc/__init__.py
omero_arc/arc_mapping.py
omero_arc/arc_packer.py
omero_arc-0.0.1.dist-info/LICENSE
omero_arc-0.0.1.dist-info/METADATA
omero_arc-0.0.1.dist-info/WHEEL
omero_arc-0.0.1.dist-info/entry_points.txt
omero_arc-0.0.1.dist-info/top_level.txt
omero_arc-0.0.1.dist-info/RECORD
