Metadata-Version: 2.1
Name: omero-arc
Version: 0.0.1
Summary: Plugin for omero-cli-transfer to export OMERO data to ARC repositories.
Author: Christoph Möhl
License: GNU GENERAL PUBLIC LICENSE
Project-URL: Homepage, https://github.com/cmohl2013/omero-arc
Classifier: Development Status :: 3 - Alpha
Classifier: Programming Language :: Python :: 3
Requires-Python: >=3.8
License-File: LICENSE
Requires-Dist: omero-py ==5.13.1
Requires-Dist: pandas
Requires-Dist: openpyxl
Provides-Extra: dev
Requires-Dist: omero-cli-transfer ; extra == 'dev'
Requires-Dist: ome-types ==0.4.2 ; extra == 'dev'
